astromath/__init__.py
astromath/astromath.py
astromath/cli.py
astromath-1.0.1.dist-info/AUTHORS.rst
astromath-1.0.1.dist-info/LICENSE
astromath-1.0.1.dist-info/METADATA
astromath-1.0.1.dist-info/WHEEL
astromath-1.0.1.dist-info/entry_points.txt
astromath-1.0.1.dist-info/top_level.txt
astromath-1.0.1.dist-info/RECORD
