Metadata-Version: 2.1
Name: astromath
Version: 1.0.1
Summary: Library for mathematical astronomy
Home-page: https://github.com/qxlsz/astromath
Author: Rajasekhar Josyula
Author-email: rajasekhar.josyula@gmail.com
License: MIT license
Keywords: astromath
Platform: UNKNOWN
Classifier: Development Status :: 2 - Pre-Alpha
Classifier: Intended Audience :: Developers
Classifier: License :: OSI Approved :: MIT License
Classifier: Natural Language :: English
Classifier: Programming Language :: Python :: 3
Classifier: Programming Language :: Python :: 3.5
Classifier: Programming Language :: Python :: 3.6
Classifier: Programming Language :: Python :: 3.7
Classifier: Programming Language :: Python :: 3.8
Requires-Python: >=3.5
